nebius/spark/connect/__init__.py
nebius/spark/connect/session.py
nebius_connect-0.1.0.dist-info/LICENSE
nebius_connect-0.1.0.dist-info/METADATA
nebius_connect-0.1.0.dist-info/WHEEL
nebius_connect-0.1.0.dist-info/top_level.txt
nebius_connect-0.1.0.dist-info/RECORD
