Metadata-Version: 2.1
Name: nebius-connect
Version: 0.1.0
Summary: Nebius AI connector for Apache Spark™
Classifier: Programming Language :: Python :: 3.8
Classifier: Programming Language :: Python :: 3.9
Classifier: Programming Language :: Python :: 3.10
Classifier: Programming Language :: Python :: 3.11
Classifier: Programming Language :: Python :: 3.12
Classifier: License :: OSI Approved :: Apache Software License
Classifier: Operating System :: OS Independent
Requires-Python: >=3.8
License-File: LICENSE
Requires-Dist: pyspark[connect] ==3.5.*
Requires-Dist: grpcio >=1.66.1
Requires-Dist: setuptools >=75.1.0 ; python_version >= "3.12"
